swarm_orchestrator/__init__.py
swarm_orchestrator/cli.py
swarm_orchestrator/config.py
swarm_orchestrator/models.py
swarm_orchestrator/consensus/__init__.py
swarm_orchestrator/consensus/election.py
swarm_orchestrator/core/__init__.py
swarm_orchestrator/core/node.py
swarm_orchestrator/core/swarm.py
swarm_orchestrator/gossip/__init__.py
swarm_orchestrator/gossip/adaptive.py
swarm_orchestrator/gossip/message.py
swarm_orchestrator/gossip/protocol.py
swarm_orchestrator/gossip/transport.py
swarm_orchestrator/metrics/__init__.py
swarm_orchestrator/metrics/collector.py
swarm_orchestrator/metrics/dashboard.py
swarm_orchestrator/metrics/energy.py
swarm_orchestrator/metrics/green_dashboard.py
swarm_orchestrator/utils/__init__.py
swarm_orchestrator/utils/display.py
iot_swarm-0.2.0.dist-info/METADATA
iot_swarm-0.2.0.dist-info/WHEEL
iot_swarm-0.2.0.dist-info/entry_points.txt
iot_swarm-0.2.0.dist-info/licenses/LICENSE
iot_swarm-0.2.0.dist-info/RECORD
