Metadata-Version: 2.4
Name: iot-swarm
Version: 0.2.0
Summary: Orchestrate AI agent swarms on edge/IoT hardware with energy-efficient gossip protocols
Author: The Swarm Orchestrator Contributors
License-Expression: MIT
License-File: LICENSE
Keywords: agents,ai,distributed,edge,gossip,iot,swarm
Classifier: Development Status :: 3 - Alpha
Classifier: Environment :: Console
Classifier: Intended Audience :: Developers
Classifier: License :: OSI Approved :: MIT License
Classifier: Operating System :: OS Independent
Classifier: Programming Language :: Python :: 3
Classifier: Programming Language :: Python :: 3.11
Classifier: Programming Language :: Python :: 3.12
Classifier: Topic :: System :: Distributed Computing
Classifier: Topic :: System :: Networking
Requires-Python: >=3.11
Requires-Dist: pydantic-settings>=2.0.0
Requires-Dist: pydantic>=2.0.0
Requires-Dist: rich>=13.0.0
Requires-Dist: toml>=0.10.0
Requires-Dist: typer[all]>=0.9.0
Provides-Extra: all
Requires-Dist: swarm-orchestrator[dev,metrics]; extra == 'all'
Provides-Extra: dev
Requires-Dist: pytest-asyncio>=0.21.0; extra == 'dev'
Requires-Dist: pytest-cov>=4.0.0; extra == 'dev'
Requires-Dist: pytest>=7.0.0; extra == 'dev'
Provides-Extra: metrics
Requires-Dist: psutil>=5.9.0; extra == 'metrics'
